proboscis_async_events/__init__.py
proboscis_async_events/messaging.py
proboscis_async_events-0.1.11.dist-info/METADATA
proboscis_async_events-0.1.11.dist-info/WHEEL
proboscis_async_events-0.1.11.dist-info/RECORD
